frigate_ai
