Metadata-Version: 2.1
Name: frigate-ai
Version: 0.0.4
Summary: Start Shipping Your Tensorflow Models! Turn your ML projects into a useable no-code demo and scalable and monetizable API. All faster than you can write a README.
Home-page: https://github.com/armaangoel78/Frigate-AI
Author: Armaan Goel
Author-email: armaangoel78@gmail.com
License: UNKNOWN
Platform: UNKNOWN
